README
rpweibo.py
setup.py
rpweibo.egg-info/PKG-INFO
rpweibo.egg-info/SOURCES.txt
rpweibo.egg-info/dependency_links.txt
rpweibo.egg-info/requires.txt
rpweibo.egg-info/top_level.txt