Metadata-Version: 1.1
Name: rpweibo
Version: 0.2.2
Summary: cURL + Python Weibo Wrapper
Home-page: https://github.com/WeCase/rpweibo
Author: Tom Li
Author-email: biergaizi@member.fsf.org
License: LGPLv3+
Download-URL: https://github.com/WeCase/rpweibo
Platform: UNKNOWN
Classifier: Development Status :: 3 - Alpha
Classifier: Environment :: Web Environment
Classifier: Intended Audience :: Developers
Classifier: License :: OSI Approved :: GNU Lesser General Public License v3 or later (LGPLv3+)
Classifier: Operating System :: POSIX :: Linux
Classifier: Programming Language :: Python :: 3 :: Only
Classifier: Topic :: Internet
Classifier: Topic :: Software Development :: Libraries :: Python Modules
